Workbook

Sheet Summary
A1: Abbott — Precedent Transaction Analysis
A2: Potential divestiture of the Nutrition and Established Pharmaceuticals (EPD) businesses • FY2024 basis • Indicative / discussion draft
A4: Headline indicative enterprise value (EV) — see Valuation tab for build, Inputs tab for assumptions.
A6: Business | B6: FY24 Sales ($bn) | C6: Est. EBITDA ($bn) | D6: EV/Sales | E6: EV/EBITDA | F6: Indicative EV ($bn)
A7: Nutrition | B7: ='Inputs & Assumptions'!B8/1000 | C7: ='Inputs & Assumptions'!B12/1000 | D7: =TEXT('Inputs & Assumptions'!B17,"0.0")&"–"&TEXT('Inputs & Assumptions'!C17,"0.0")&"x" | E7: =TEXT('Inputs & Assumptions'!B18,"0.0")&"–"&TEXT('Inputs & Assumptions'!C18,"0.0")&"x" | F7: =TEXT(Valuation!D8/1000,"0")&"–"&TEXT(Valuation!E8/1000,"0")&"bn"
A8: Established Pharmaceuticals (EPD) | B8: ='Inputs & Assumptions'!C8/1000 | C8: ='Inputs & Assumptions'!C12/1000 | D8: =TEXT('Inputs & Assumptions'!D17,"0.0")&"–"&TEXT('Inputs & Assumptions'!E17,"0.0")&"x" | E8: =TEXT('Inputs & Assumptions'!D18,"0.0")&"–"&TEXT('Inputs & Assumptions'!E18,"0.0")&"x" | F8: =TEXT(Valuation!D14/1000,"0")&"–"&TEXT(Valuation!E14/1000,"0")&"bn"
A9: Combined | B9: =('Inputs & Assumptions'!B8+'Inputs & Assumptions'!C8)/1000 | C9: =('Inputs & Assumptions'!B12+'Inputs & Assumptions'!C12)/1000 | D9: — | E9: — | F9: =TEXT((Valuation!D8+Valuation!D14)/1000,"0")&"–"&TEXT((Valuation!E8+Valuation!E14)/1000,"0")&"bn"
A11: Key points
A12: • EPD is the cleaner asset — high-growth (+9.2%), high-margin (23.7%) emerging-market branded generics; sits at the premium end of the branded-generics deal range.
A13: • Nutrition is two-speed: attractive, growing adult/medical nutrition (Ensure, Glucerna) vs. a structurally challenged infant-formula half (Similac) carrying an NEC product-liability litigation overhang.
A14: • Peak infant-formula comps (Reckitt/MJN 17.4x, Nestlé/Pfizer ~20x) are discounted for Nutrition's blended mix and litigation risk.
A15: • Sum-of-the-parts optionality: selling adult nutrition at consumer-health multiples while ring-fencing infant formula could exceed the blended range.
A16: • EBITDA is ESTIMATED (Abbott discloses segment operating margin, not EBITDA). Indicative only — not investment advice; refine with carve-out QoE financials.
A18: Tabs: Summary · Inputs & Assumptions (drivers) · Nutrition Comps · EPD Comps · Valuation (build)

Sheet Inputs & Assumptions
A1: Abbott — Nutrition & EPD Divestiture | Inputs & Assumptions
A2: Blue cells are inputs — change them and the Valuation/Summary tabs recalc. FY2024 reported segment basis. EBITDA is estimated (see notes).
A4: Blue figures are drivers. $ figures in US$ millions unless noted.
A6: Target sizing (FY2024)
A7: Metric | B7: Nutrition | C7: EPD | D7: Source / note
A8: FY24 net sales ($m) | B8: 8410 | C8: 5190 | D8: Abbott FY24 segment reporting (~$8.4bn / ~$5.2bn)
A9: FY24 segment operating margin | B9: 0.179 | C9: 0.237 | D9: Disclosed: Nutrition 17.9%, EPD 23.7%
A10: Assumed D&A add-back (% sales) | B10: 0.0375 | C10: 0.0275 | D10: Estimate — Nutrition more capital-intensive
A11: Implied segment operating earnings ($m) | B11: =B8*B9 | C11: =C8*C9 | D11: =sales x operating margin
A12: Estimated EBITDA ($m) | B12: =B8*(B9+B10) | C12: =C8*(C9+C10) | D12: =operating earnings + D&A add-back
A13: Implied EBITDA margin | B13: =B12/B8 | C13: =C12/C8
A15: Selected multiple ranges (judgement)
A16: Multiple | B16: Nutrition low | C16: Nutrition high | D16: EPD low | E16: EPD high
A17: EV / Sales | B17: 2 | C17: 3 | D17: 2.5 | E17: 3.5
A18: EV / EBITDA | B18: 11 | C18: 15 | D18: 11 | E18: 14
A20: Rationale
A21: • Nutrition: peak infant-formula comps (Reckitt/MJN 17.4x, Nestlé/Pfizer ~20x) discounted for blended adult+pediatric mix and the NEC litigation overhang.
A22: • EPD: premium end of branded-generics range (STADA 13.4x / Krka ~11.5x) given +9.2% growth and 23.7% margin; above mature Western generics (Hikma/Richter ~6x).
A23: • EBITDA is ESTIMATED — Abbott discloses segment operating margin, not EBITDA. Refine with carve-out quality-of-earnings financials.

Sheet Nutrition Comps
A1: Nutrition Comps
A2: Precedent transactions — infant + adult/medical nutrition. Multiples as reported by public sources; treat as directional.
A4: Year | B4: Acquirer | C4: Target | D4: EV ($bn) | E4: EV/Sales | F4: EV/EBITDA | G4: Notes
A5: 2007 | B5: Danone | C5: Numico | D5: 16.8 | E5: 4.5 | F5: 22 | G5: Baby + medical nutrition; peak strategic multiple
A6: 2007 | B6: Nestlé | C6: Gerber (from Novartis) | D6: 5.5 | E6: 2.8 | F6: 20 | G6: EBITDA mult. est.; made Nestlé #1 baby food
A7: 2012 | B7: Nestlé | C7: Pfizer Nutrition | D7: 11.85 | E7: 5 | F7: 22 | G7: ~$2.1bn sales / ~$0.5bn EBITDA (2011); EM (China) entry
A8: 2017 | B8: Danone | C8: WhiteWave | D8: 12.5 | E8: 2.7 | F8: 20 | G8: Organic/plant-based (not infant); lower-multiple bookend
A9: 2017 | B9: Reckitt Benckiser | C9: Mead Johnson | D9: 17.9 | E9: 4.4 | F9: 17.4 | G9: Pure-play infant formula; closest single comp (~14x w/ synergies)
A10: 2021 | B10: Nestlé | C10: The Bountiful Company | D10: 5.75 | E10: 2.7 | F10: 17 | G10: Vitamins/supplements; adult-nutrition-adjacent
A11: Median | D11: =MEDIAN(D5:D10) | E11: =MEDIAN(E5:E10) | F11: =MEDIAN(F5:F10)
A12: Mean | D12: =AVERAGE(D5:D10) | E12: =AVERAGE(E5:E10) | F12: =AVERAGE(F5:F10)

Sheet EPD Comps
A1: EPD Comps
A2: Precedent transactions — branded / emerging-market generics. Listed reads for context: Krka ~11.5x, Hikma ~6.3x, Richter ~6x EV/EBITDA.
A4: Year | B4: Acquirer | C4: Target | D4: EV ($bn) | E4: EV/Sales | F4: EV/EBITDA | G4: Notes
A5: 2014 | B5: Sun Pharma | C5: Ranbaxy | D5: 4 | E5: 2.2 | G5: Incl. debt; low-margin target (EBITDA mult. n/m); India/EM
A6: 2015 | B6: Teva | C6: Allergan Generics (Actavis) | D6: 40.5 | E6: 3.6 | F6: 11.5 | G6: EBITDA mult. est.; global generics scale
A7: 2016 | B7: Mylan | C7: Meda | D7: 9.9 | E7: 3.3 | F7: 10.5 | G7: 8.9x w/ synergies; ~10–11x reported; branded/specialty + EM/OTC
A8: 2017 | B8: Bain / Cinven | C8: STADA | D8: 5.7 | E8: 2.4 | F8: 13.4 | G8: EUR 5.32bn; PE take-private; branded generics + consumer health
A9: 2018 | B9: Advent | C9: Zentiva (Sanofi EU gen.) | D9: 2.1 | E9: 2.5 | F9: 10.3 | G9: EUR ~1.9bn; EU/EM branded-generics carve-out
A10: 2025 | B10: CapVest | C10: STADA (majority stake) | D10: 10 | E10: 3 | F10: 11.3 | G10: Reported ~EUR 10bn; latest large branded-generics print
A11: Median | D11: =MEDIAN(D5:D10) | E11: =MEDIAN(E5:E10) | F11: =MEDIAN(F5:F10)
A12: Mean | D12: =AVERAGE(D5:D10) | E12: =AVERAGE(E5:E10) | F12: =AVERAGE(F5:F10)

Sheet Valuation
A1: Valuation — Implied Enterprise Value
A2: Driven by Inputs & Assumptions tab. $ in US$ millions; EV summary in $bn.
A4: Nutrition
A5: Method | B5: Multiple low | C5: Multiple high | D5: EV low ($m) | E5: EV high ($m) | F5: EV midpoint ($bn)
A6: EV / Sales | B6: ='Inputs & Assumptions'!B17 | C6: ='Inputs & Assumptions'!C17 | D6: ='Inputs & Assumptions'!B8*B6 | E6: ='Inputs & Assumptions'!B8*C6 | F6: =AVERAGE(D6:E6)/1000
A7: EV / EBITDA | B7: ='Inputs & Assumptions'!B18 | C7: ='Inputs & Assumptions'!C18 | D7: ='Inputs & Assumptions'!B12*B7 | E7: ='Inputs & Assumptions'!B12*C7 | F7: =AVERAGE(D7:E7)/1000
A8: Blended indicative EV | D8: =MIN(D6:E7) | E8: =MAX(D6:E7) | F8: =AVERAGE(D8:E8)/1000
A10: Established Pharmaceuticals (EPD)
A11: Method | B11: Multiple low | C11: Multiple high | D11: EV low ($m) | E11: EV high ($m) | F11: EV midpoint ($bn)
A12: EV / Sales | B12: ='Inputs & Assumptions'!D17 | C12: ='Inputs & Assumptions'!E17 | D12: ='Inputs & Assumptions'!C8*B12 | E12: ='Inputs & Assumptions'!C8*C12 | F12: =AVERAGE(D12:E12)/1000
A13: EV / EBITDA | B13: ='Inputs & Assumptions'!D18 | C13: ='Inputs & Assumptions'!E18 | D13: ='Inputs & Assumptions'!C12*B13 | E13: ='Inputs & Assumptions'!C12*C13 | F13: =AVERAGE(D13:E13)/1000
A14: Blended indicative EV | D14: =MIN(D12:E13) | E14: =MAX(D12:E13) | F14: =AVERAGE(D14:E14)/1000
A16: Combined (Nutrition + EPD)
D17: EV low ($m) | E17: EV high ($m) | F17: EV midpoint ($bn)
A18: Total indicative enterprise value | D18: =D8+D14 | E18: =E8+E14 | F18: =AVERAGE(D18:E18)/1000
